ai_enterprise_agent/__init__.py
ai_enterprise_agent/agent.py
ai_enterprise_agent/interface/__init__.py
ai_enterprise_agent/interface/agent.py
ai_enterprise_agent/interface/chat_history.py
ai_enterprise_agent/interface/settings.py
ai_enterprise_agent/interface/vector_search.py
ai_enterprise_agent/services/__init__.py
ai_enterprise_agent/services/chains/__init__.py
ai_enterprise_agent/services/chains/chain.py
ai_enterprise_agent/services/chains/open_api_chain.py
ai_enterprise_agent/services/chains/orchestrator_chain.py
ai_enterprise_agent/services/chains/sequential_chain.py
ai_enterprise_agent/services/chains/simple_chain.py
ai_enterprise_agent/services/chains/sql_chain.py
ai_enterprise_agent/services/chains/vector_store_chain.py
ai_enterprise_agent/services/chat_history/__init__.py
ai_enterprise_agent/services/chat_history/memory.py
ai_enterprise_agent/services/chat_history/memory_chat_history.py
ai_enterprise_agent/services/chat_history/memory_chat_redis.py
ai_enterprise_agent/services/ingestion/__init__.py
ai_enterprise_agent/services/ingestion/csv_loader.py
ai_enterprise_agent/services/ingestion/ingestion.py
ai_enterprise_agent/services/ingestion/loader.py
ai_enterprise_agent/services/ingestion/msft_loader.py
ai_enterprise_agent/services/ingestion/pdf_loader.py
ai_enterprise_agent/services/ingestion/txt_loader.py
ai_enterprise_agent/services/llm/__init__.py
ai_enterprise_agent/services/llm/azure.py
ai_enterprise_agent/services/llm/google.py
ai_enterprise_agent/services/llm/model.py
ai_enterprise_agent/services/vector_store/__init__.py
ai_enterprise_agent/services/vector_store/aws.py
ai_enterprise_agent/services/vector_store/azure.py
ai_enterprise_agent/services/vector_store/embedding.py
ai_enterprise_agent/services/vector_store/pinecone.py
ai_enterprise_agent/services/vector_store/vector_store.py
ai_enterprise_agent/utils/__init__.py
ai_enterprise_agent/utils/fetch_helper.py
ai_enterprise_agent-0.0.9.dist-info/LICENSE
ai_enterprise_agent-0.0.9.dist-info/METADATA
ai_enterprise_agent-0.0.9.dist-info/WHEEL
ai_enterprise_agent-0.0.9.dist-info/top_level.txt
ai_enterprise_agent-0.0.9.dist-info/RECORD
