Metadata-Version: 2.1
Name: ai-enterprise-agent
Version: 0.0.9
Summary: AI Agent simplifies the implementation and use of generative AI with LangChain.
Author: Author
Author-email: autor@autor.com.br
License: Apache 2.0 License
Keywords: ai ai-agent agent assistant enterprise
Requires-Python: >=3.9
License-File: LICENSE
Requires-Dist: aiohttp ==3.9.3
Requires-Dist: aiosignal ==1.3.1
Requires-Dist: annotated-types ==0.6.0
Requires-Dist: anyio ==4.3.0
Requires-Dist: attrs ==23.2.0
Requires-Dist: azure-ai-documentintelligence ==1.0.0b3
Requires-Dist: azure-common ==1.1.28
Requires-Dist: azure-core ==1.30.1
Requires-Dist: azure-identity ==1.15.0
Requires-Dist: azure-search ==1.0.0b2
Requires-Dist: azure-search-documents ==11.4.0
Requires-Dist: boto3 ==1.34.70
Requires-Dist: botocore ==1.34.70
Requires-Dist: cachetools ==5.3.3
Requires-Dist: certifi ==2024.2.2
Requires-Dist: cffi ==1.16.0
Requires-Dist: charset-normalizer ==3.3.2
Requires-Dist: colorama ==0.4.6
Requires-Dist: cryptography ==42.0.5
Requires-Dist: dataclasses-json ==0.6.4
Requires-Dist: distro ==1.9.0
Requires-Dist: frozenlist ==1.4.1
Requires-Dist: google-ai-generativelanguage ==0.4.0
Requires-Dist: google-api-core ==2.17.1
Requires-Dist: google-auth ==2.28.2
Requires-Dist: google-generativeai ==0.4.1
Requires-Dist: googleapis-common-protos ==1.63.0
Requires-Dist: greenlet ==3.0.3
Requires-Dist: grpcio ==1.62.1
Requires-Dist: grpcio-status ==1.62.1
Requires-Dist: h11 ==0.14.0
Requires-Dist: httpcore ==1.0.4
Requires-Dist: httpx ==0.27.0
Requires-Dist: idna ==3.6
Requires-Dist: isodate ==0.6.1
Requires-Dist: jmespath ==1.0.1
Requires-Dist: jsonpatch ==1.33
Requires-Dist: jsonpointer ==2.4
Requires-Dist: langchain ==0.1.14
Requires-Dist: langchain-community ==0.0.31
Requires-Dist: langchain-core ==0.1.37
Requires-Dist: langchain-google-genai ==0.0.11
Requires-Dist: langchain-openai ==0.1.1
Requires-Dist: langchain-pinecone ==0.0.3
Requires-Dist: langchain-text-splitters ==0.0.1
Requires-Dist: langsmith ==0.1.27
Requires-Dist: marshmallow ==3.21.1
Requires-Dist: msal ==1.28.0
Requires-Dist: msal-extensions ==1.1.0
Requires-Dist: msrest ==0.7.1
Requires-Dist: multidict ==6.0.5
Requires-Dist: mypy-extensions ==1.0.0
Requires-Dist: nanoid ==2.0.0
Requires-Dist: numpy ==1.26.4
Requires-Dist: oauthlib ==3.2.2
Requires-Dist: openai ==1.14.3
Requires-Dist: opensearch-py ==2.5.0
Requires-Dist: orjson ==3.9.15
Requires-Dist: packaging ==23.2
Requires-Dist: pinecone-client ==3.2.2
Requires-Dist: portalocker ==2.8.2
Requires-Dist: proto-plus ==1.23.0
Requires-Dist: protobuf ==4.25.3
Requires-Dist: psycopg2 ==2.9.9
Requires-Dist: psycopg2-binary ==2.9.9
Requires-Dist: pyasn1 ==0.5.1
Requires-Dist: pyasn1-modules ==0.3.0
Requires-Dist: pycparser ==2.21
Requires-Dist: pydantic ==2.6.4
Requires-Dist: pydantic-core ==2.16.3
Requires-Dist: PyJWT ==2.8.0
Requires-Dist: pypdf ==4.2.0
Requires-Dist: python-dateutil ==2.9.0.post0
Requires-Dist: PyYAML ==6.0.1
Requires-Dist: redis ==5.0.3
Requires-Dist: regex ==2023.12.25
Requires-Dist: requests ==2.31.0
Requires-Dist: requests-oauthlib ==2.0.0
Requires-Dist: rsa ==4.9
Requires-Dist: s3transfer ==0.10.1
Requires-Dist: setuptools ==69.2.0
Requires-Dist: six ==1.16.0
Requires-Dist: sniffio ==1.3.1
Requires-Dist: SQLAlchemy ==2.0.29
Requires-Dist: tenacity ==8.2.3
Requires-Dist: tiktoken ==0.5.2
Requires-Dist: tqdm ==4.66.2
Requires-Dist: typing-inspect ==0.9.0
Requires-Dist: typing-extensions ==4.10.0
Requires-Dist: urllib3 ==1.26.18
Requires-Dist: yarl ==1.9.4
